ipv64.py
ipv64-0.5.3.dist-info/LICENSE
ipv64-0.5.3.dist-info/METADATA
ipv64-0.5.3.dist-info/WHEEL
ipv64-0.5.3.dist-info/top_level.txt
ipv64-0.5.3.dist-info/RECORD
