Metadata-Version: 2.1
Name: ipv64
Version: 0.5.3
Summary: Updater for ipv64.net
Home-page: https://github.com/syncip/ipv64
Author: R60
Author-email: pypi.nmvk0@getrekt.win
Keywords: ipv64,dyndns,updater
License-File: LICENSE
Requires-Dist: requests (==2.28.1)
Requires-Dist: argparse (==1.4.0)
